
{"items":[{"name":"Refinity.Benchmark","href":"Refinity.Benchmark.html","topicHref":"Refinity.Benchmark.html","topicUid":"Refinity.Benchmark","items":[{"name":"BenchmarkUtility","href":"Refinity.Benchmark.BenchmarkUtility.html","topicHref":"Refinity.Benchmark.BenchmarkUtility.html","topicUid":"Refinity.Benchmark.BenchmarkUtility"}]},{"name":"Refinity.Benchmark.Models","href":"Refinity.Benchmark.Models.html","topicHref":"Refinity.Benchmark.Models.html","topicUid":"Refinity.Benchmark.Models","items":[{"name":"BenchmarkModels","href":"Refinity.Benchmark.Models.BenchmarkModels.html","topicHref":"Refinity.Benchmark.Models.BenchmarkModels.html","topicUid":"Refinity.Benchmark.Models.BenchmarkModels"}]},{"name":"Refinity.Conversion","href":"Refinity.Conversion.html","topicHref":"Refinity.Conversion.html","topicUid":"Refinity.Conversion","items":[{"name":"ConvertUtility","href":"Refinity.Conversion.ConvertUtility.html","topicHref":"Refinity.Conversion.ConvertUtility.html","topicUid":"Refinity.Conversion.ConvertUtility"},{"name":"LogEntry","href":"Refinity.Conversion.LogEntry.html","topicHref":"Refinity.Conversion.LogEntry.html","topicUid":"Refinity.Conversion.LogEntry"}]},{"name":"Refinity.Date","href":"Refinity.Date.html","topicHref":"Refinity.Date.html","topicUid":"Refinity.Date","items":[{"name":"DateDifference","href":"Refinity.Date.DateDifference.html","topicHref":"Refinity.Date.DateDifference.html","topicUid":"Refinity.Date.DateDifference"},{"name":"DateRangeModel","href":"Refinity.Date.DateRangeModel.html","topicHref":"Refinity.Date.DateRangeModel.html","topicUid":"Refinity.Date.DateRangeModel"},{"name":"DateUtility","href":"Refinity.Date.DateUtility.html","topicHref":"Refinity.Date.DateUtility.html","topicUid":"Refinity.Date.DateUtility"}]},{"name":"Refinity.Enums","href":"Refinity.Enums.html","topicHref":"Refinity.Enums.html","topicUid":"Refinity.Enums","items":[{"name":"EnumBenchmarkResult","href":"Refinity.Enums.EnumBenchmarkResult.html","topicHref":"Refinity.Enums.EnumBenchmarkResult.html","topicUid":"Refinity.Enums.EnumBenchmarkResult"},{"name":"EnumColor","href":"Refinity.Enums.EnumColor.html","topicHref":"Refinity.Enums.EnumColor.html","topicUid":"Refinity.Enums.EnumColor"},{"name":"EnumCurrency","href":"Refinity.Enums.EnumCurrency.html","topicHref":"Refinity.Enums.EnumCurrency.html","topicUid":"Refinity.Enums.EnumCurrency"},{"name":"EnumFileTypes","href":"Refinity.Enums.EnumFileTypes.html","topicHref":"Refinity.Enums.EnumFileTypes.html","topicUid":"Refinity.Enums.EnumFileTypes"},{"name":"EnumLanguageCodes","href":"Refinity.Enums.EnumLanguageCodes.html","topicHref":"Refinity.Enums.EnumLanguageCodes.html","topicUid":"Refinity.Enums.EnumLanguageCodes"},{"name":"EnumLogLevel","href":"Refinity.Enums.EnumLogLevel.html","topicHref":"Refinity.Enums.EnumLogLevel.html","topicUid":"Refinity.Enums.EnumLogLevel"},{"name":"EnumMonths","href":"Refinity.Enums.EnumMonths.html","topicHref":"Refinity.Enums.EnumMonths.html","topicUid":"Refinity.Enums.EnumMonths"},{"name":"EnumPressureUnits","href":"Refinity.Enums.EnumPressureUnits.html","topicHref":"Refinity.Enums.EnumPressureUnits.html","topicUid":"Refinity.Enums.EnumPressureUnits"},{"name":"EnumScaleGrams","href":"Refinity.Enums.EnumScaleGrams.html","topicHref":"Refinity.Enums.EnumScaleGrams.html","topicUid":"Refinity.Enums.EnumScaleGrams"},{"name":"EnumScaleJoules","href":"Refinity.Enums.EnumScaleJoules.html","topicHref":"Refinity.Enums.EnumScaleJoules.html","topicUid":"Refinity.Enums.EnumScaleJoules"},{"name":"EnumScaleLiters","href":"Refinity.Enums.EnumScaleLiters.html","topicHref":"Refinity.Enums.EnumScaleLiters.html","topicUid":"Refinity.Enums.EnumScaleLiters"},{"name":"EnumScaleMeters","href":"Refinity.Enums.EnumScaleMeters.html","topicHref":"Refinity.Enums.EnumScaleMeters.html","topicUid":"Refinity.Enums.EnumScaleMeters"},{"name":"EnumScaleMiles","href":"Refinity.Enums.EnumScaleMiles.html","topicHref":"Refinity.Enums.EnumScaleMiles.html","topicUid":"Refinity.Enums.EnumScaleMiles"},{"name":"EnumScaleOnces","href":"Refinity.Enums.EnumScaleOnces.html","topicHref":"Refinity.Enums.EnumScaleOnces.html","topicUid":"Refinity.Enums.EnumScaleOnces"},{"name":"EnumScalePascal","href":"Refinity.Enums.EnumScalePascal.html","topicHref":"Refinity.Enums.EnumScalePascal.html","topicUid":"Refinity.Enums.EnumScalePascal"},{"name":"EnumScaleTime","href":"Refinity.Enums.EnumScaleTime.html","topicHref":"Refinity.Enums.EnumScaleTime.html","topicUid":"Refinity.Enums.EnumScaleTime"},{"name":"EnumScaleVolts","href":"Refinity.Enums.EnumScaleVolts.html","topicHref":"Refinity.Enums.EnumScaleVolts.html","topicUid":"Refinity.Enums.EnumScaleVolts"},{"name":"EnumScaleWatts","href":"Refinity.Enums.EnumScaleWatts.html","topicHref":"Refinity.Enums.EnumScaleWatts.html","topicUid":"Refinity.Enums.EnumScaleWatts"},{"name":"EnumTemperatureUnits","href":"Refinity.Enums.EnumTemperatureUnits.html","topicHref":"Refinity.Enums.EnumTemperatureUnits.html","topicUid":"Refinity.Enums.EnumTemperatureUnits"},{"name":"EnumUnitSystem","href":"Refinity.Enums.EnumUnitSystem.html","topicHref":"Refinity.Enums.EnumUnitSystem.html","topicUid":"Refinity.Enums.EnumUnitSystem"},{"name":"EnumWeekDays","href":"Refinity.Enums.EnumWeekDays.html","topicHref":"Refinity.Enums.EnumWeekDays.html","topicUid":"Refinity.Enums.EnumWeekDays"},{"name":"EnumWeekDaysShort","href":"Refinity.Enums.EnumWeekDaysShort.html","topicHref":"Refinity.Enums.EnumWeekDaysShort.html","topicUid":"Refinity.Enums.EnumWeekDaysShort"},{"name":"EnumsUtility","href":"Refinity.Enums.EnumsUtility.html","topicHref":"Refinity.Enums.EnumsUtility.html","topicUid":"Refinity.Enums.EnumsUtility"}]},{"name":"Refinity.Finance","href":"Refinity.Finance.html","topicHref":"Refinity.Finance.html","topicUid":"Refinity.Finance","items":[{"name":"FinanceUtility","href":"Refinity.Finance.FinanceUtility.html","topicHref":"Refinity.Finance.FinanceUtility.html","topicUid":"Refinity.Finance.FinanceUtility"}]},{"name":"Refinity.Geometry","href":"Refinity.Geometry.html","topicHref":"Refinity.Geometry.html","topicUid":"Refinity.Geometry","items":[{"name":"CoordinateModel","href":"Refinity.Geometry.CoordinateModel.html","topicHref":"Refinity.Geometry.CoordinateModel.html","topicUid":"Refinity.Geometry.CoordinateModel"},{"name":"GeometryUtility","href":"Refinity.Geometry.GeometryUtility.html","topicHref":"Refinity.Geometry.GeometryUtility.html","topicUid":"Refinity.Geometry.GeometryUtility"}]},{"name":"Refinity.Logging","href":"Refinity.Logging.html","topicHref":"Refinity.Logging.html","topicUid":"Refinity.Logging","items":[{"name":"LoggingUtility","href":"Refinity.Logging.LoggingUtility.html","topicHref":"Refinity.Logging.LoggingUtility.html","topicUid":"Refinity.Logging.LoggingUtility"}]},{"name":"Refinity.Math","href":"Refinity.Math.html","topicHref":"Refinity.Math.html","topicUid":"Refinity.Math","items":[{"name":"LinearRegressionModel","href":"Refinity.Math.LinearRegressionModel.html","topicHref":"Refinity.Math.LinearRegressionModel.html","topicUid":"Refinity.Math.LinearRegressionModel"},{"name":"MathUtility","href":"Refinity.Math.MathUtility.html","topicHref":"Refinity.Math.MathUtility.html","topicUid":"Refinity.Math.MathUtility"}]},{"name":"Refinity.Strings","href":"Refinity.Strings.html","topicHref":"Refinity.Strings.html","topicUid":"Refinity.Strings","items":[{"name":"StringsUtility","href":"Refinity.Strings.StringsUtility.html","topicHref":"Refinity.Strings.StringsUtility.html","topicUid":"Refinity.Strings.StringsUtility"}]}],"memberLayout":"SamePage","pdf":false}
